{
   "worker_count": 3,
   "expertise_scores": [
      [
         0.7861430386358229,
         0.505894465772413,
         0.40340544732478784
      ],
      [
         0.6431547274569637,
         0.26146139272896907,
         0.5807366759313642
      ],
      [
         0.06515273428861522,
         0.10164700270331314,
         0.147238395894436
      ],
      [
         0.20157804455758666,
         0.21359085905779912,
         0.09604205052822412
      ],
      [
         0.3789233507902397,
         0.4780975589156021,
         0.3788451169367937
      ],
      [
         0.3760451300831464,
         0.21359494102558269,
         0.10072240480078112
      ],
      [
         0.6812262516618292,
         0.14671540621536694,
         0.5813711142663424
      ],
      [
         0.4408754054536435,
         0.12392579129562506,
         0.16123859002806473
      ],
      [
         0.14683021868110263,
         0.40707115991177817,
         0.5009507419619345
      ],
      [
         0.3562173898190121,
         0.10879479798526043,
         0.48539514498148206
      ]
   ],
   "mv_f1_micro": [
      0.7023511755877939,
      0.6173086543271635,
      0.10955477738869436,
      0.19609804902451222,
      0.503751875937969,
      0.2751375687843922,
      0.5917958979489745,
      0.2591295647823912,
      0.42971485742871435,
      0.36518259129564784
   ],
   "mv_f1_macro": [
      0.7024511701955333,
      0.6160486947278146,
      0.10901432667158319,
      0.19587370850922028,
      0.5035714210293251,
      0.27484792489593,
      0.5904352338692023,
      0.25971626547885585,
      0.4288421582639897,
      0.3649507759602306
   ],
   "mv_f1_weighted": [
      0.702392109303143,
      0.6166344903311727,
      0.10961448562490483,
      0.19646056490766511,
      0.5036789264908209,
      0.2749410253634885,
      0.5914244708977848,
      0.2591963856216654,
      0.42966745088065245,
      0.3653965272839083
   ],
   "ct_f1_micro": [
      0.8124062031015508,
      0.6773386693346674,
      0.07553776888444222,
      0.21960980490245122,
      0.5417708854427213,
      0.3731865932966483,
      0.6843421710855427,
      0.4307153576788394,
      0.5142571285642822,
      0.49674837418709356
   ],
   "ct_f1_macro": [
      0.8130284733981861,
      0.6766162037614972,
      0.07535841527038405,
      0.21910261740661355,
      0.5413029893025225,
      0.3715385525896917,
      0.6836289804578121,
      0.43026021834536515,
      0.5136254793890547,
      0.4971022833072771
   ],
   "ct_f1_weighted": [
      0.8124744529431537,
      0.6769757083607825,
      0.07560856163228692,
      0.21982810319772625,
      0.5416594534972202,
      0.37224209206376807,
      0.684732134311932,
      0.4303871519700083,
      0.5146853113907893,
      0.4967494699581272
   ],
   "gt": [
      7,
      7,
      7,
      7,
      7,
      7,
      7,
      7,
      7,
      7,
      7,
      7,
      7,
      7,
      7,
      7,
      7,
      7,
      7,
      7,
      7,
      7,
      7,
      7,
      7,
      7,
      7,
      7,
      7,
      7,
      7,
      7,
      7,
      7,
      7,
      7,
      7,
      7,
      7,
      7,
      7,
      7,
      7,
      7,
      7,
      7,
      7,
      7,
      7,
      7,
      7,
      7,
      7,
      7,
      7,
      7,
      7,
      7,
      7,
      7,
      7,
      7,
      7,
      7,
      7,
      7,
      7,
      7,
      7,
      7,
      7,
      7,
      7,
      7,
      7,
      7,
      7,
      7,
      7,
      7,
      7,
      7,
      7,
      7,
      7,
      7,
      7,
      7,
      7,
      7,
      7,
      7,
      7,
      7,
      7,
      7,
      7,
      7,
      7,
      7,
      7,
      7,
      7,
      7,
      7,
      7,
      7,
      7,
      7,
      7,
      7,
      7,
      7,
      7,
      7,
      7,
      7,
      7,
      7,
      7,
      7,
      7,
      7,
      7,
      7,
      7,
      7,
      7,
      7,
      7,
      7,
      7,
      7,
      7,
      7,
      7,
      9,
      9,
      9,
      9,
      9,
      9,
      9,
      9,
      9,
      9,
      9,
      9,
      9,
      9,
      9,
      9,
      9,
      9,
      9,
      9,
      9,
      9,
      9,
      9,
      9,
      9,
      9,
      9,
      9,
      9,
      9,
      9,
      9,
      9,
      9,
      9,
      9,
      9,
      9,
      9,
      9,
      9,
      9,
      9,
      9,
      9,
      9,
      9,
      9,
      9,
      9,
      9,
      9,
      9,
      9,
      9,
      9,
      9,
      9,
      9,
      9,
      9,
      9,
      9,
      9,
      9,
      9,
      9,
      9,
      9,
      9,
      9,
      9,
      9,
      9,
      9,
      9,
      9,
      9,
      9,
      9,
      9,
      9,
      9,
      9,
      9,
      9,
      9,
      9,
      9,
      9,
      9,
      9,
      9,
      9,
      9,
      9,
      9,
      9,
      9,
      9,
      9,
      9,
      9,
      9,
      9,
      9,
      9,
      9,
      9,
      9,
      9,
      9,
      9,
      9,
      9,
      9,
      9,
      9,
      9,
      9,
      9,
      9,
      9,
      9,
      9,
      9,
      9,
      9,
      9,
      9,
      9,
      9,
      9,
      9,
      9,
      2,
      2,
      2,
      2,
      2,
      2,
      2,
      2,
      2,
      2,
      2,
      2,
      2,
      2,
      2,
      2,
      2,
      2,
      2,
      2,
      2,
      2,
      2,
      2,
      2,
      2,
      2,
      2,
      2,
      2,
      2,
      2,
      2,
      2,
      2,
      2,
      2,
      2,
      2,
      2,
      2,
      2,
      2,
      2,
      2,
      2,
      2,
      2,
      2,
      2,
      2,
      2,
      2,
      2,
      2,
      2,
      2,
      2,
      2,
      2,
      2,
      2,
      2,
      2,
      2,
      2,
      2,
      2,
      2,
      2,
      2,
      2,
      2,
      2,
      2,
      2,
      2,
      2,
      2,
      2,
      2,
      2,
      2,
      2,
      2,
      2,
      2,
      2,
      2,
      2,
      2,
      2,
      2,
      2,
      2,
      2,
      2,
      2,
      2,
      2,
      2,
      2,
      2,
      2,
      2,
      2,
      2,
      2,
      2,
      2,
      2,
      2,
      2,
      2,
      2,
      2,
      2,
      2,
      2,
      2,
      2,
      2,
      2,
      2,
      2,
      2,
      2,
      2,
      2,
      2,
      2,
      2,
      2,
      2,
      2,
      6,
      6,
      6,
      6,
      6,
      6,
      6,
      6,
      6,
      6,
      6,
      6,
      6,
      6,
      6,
      6,
      6,
      6,
      6,
      6,
      6,
      6,
      6,
      6,
      6,
      6,
      6,
      6,
      6,
      6,
      6,
      6,
      6,
      6,
      6,
      6,
      6,
      6,
      6,
      6,
      6,
      6,
      6,
      6,
      6,
      6,
      6,
      6,
      6,
      6,
      6,
      6,
      6,
      6,
      6,
      6,
      6,
      6,
      6,
      6,
      6,
      6,
      6,
      6,
      6,
      6,
      6,
      6,
      6,
      6,
      6,
      6,
      6,
      6,
      6,
      6,
      6,
      6,
      6,
      6,
      6,
      6,
      6,
      6,
      6,
      6,
      6,
      6,
      6,
      6,
      6,
      6,
      6,
      6,
      6,
      6,
      6,
      6,
      6,
      6,
      6,
      6,
      6,
      6,
      6,
      6,
      6,
      6,
      6,
      6,
      6,
      6,
      6,
      6,
      6,
      6,
      6,
      6,
      6,
      6,
      6,
      6,
      6,
      6,
      6,
      6,
      6,
      6,
      6,
      6,
      6,
      6,
      6,
      6,
      13,
      13,
      13,
      13,
      13,
      13,
      13,
      13,
      13,
      13,
      13,
      13,
      13,
      13,
      13,
      13,
      13,
      13,
      13,
      13,
      13,
      13,
      13,
      13,
      13,
      13,
      13,
      13,
      13,
      13,
      13,
      13,
      13,
      13,
      13,
      13,
      13,
      13,
      13,
      13,
      13,
      13,
      13,
      13,
      13,
      13,
      13,
      13,
      13,
      13,
      13,
      13,
      13,
      13,
      13,
      13,
      13,
      13,
      13,
      13,
      13,
      13,
      13,
      13,
      13,
      13,
      13,
      13,
      13,
      13,
      13,
      13,
      13,
      13,
      13,
      13,
      13,
      13,
      13,
      13,
      13,
      13,
      13,
      13,
      13,
      13,
      13,
      13,
      13,
      13,
      13,
      13,
      13,
      13,
      13,
      13,
      13,
      13,
      13,
      13,
      13,
      13,
      13,
      13,
      13,
      13,
      13,
      13,
      13,
      13,
      13,
      13,
      13,
      13,
      13,
      13,
      13,
      13,
      13,
      13,
      13,
      13,
      13,
      13,
      13,
      13,
      13,
      13,
      13,
      13,
      13,
      13,
      13,
      13,
      13,
      13,
      8,
      8,
      8,
      8,
      8,
      8,
      8,
      8,
      8,
      8,
      8,
      8,
      8,
      8,
      8,
      8,
      8,
      8,
      8,
      8,
      8,
      8,
      8,
      8,
      8,
      8,
      8,
      8,
      8,
      8,
      8,
      8,
      8,
      8,
      8,
      8,
      8,
      8,
      8,
      8,
      8,
      8,
      8,
      8,
      8,
      8,
      8,
      8,
      8,
      8,
      8,
      8,
      8,
      8,
      8,
      8,
      8,
      8,
      8,
      8,
      8,
      8,
      8,
      8,
      8,
      8,
      8,
      8,
      8,
      8,
      8,
      8,
      8,
      8,
      8,
      8,
      8,
      8,
      8,
      8,
      8,
      8,
      8,
      8,
      8,
      8,
      8,
      8,
      8,
      8,
      8,
      8,
      8,
      8,
      8,
      8,
      8,
      8,
      8,
      8,
      8,
      8,
      8,
      8,
      8,
      8,
      8,
      8,
      8,
      8,
      8,
      8,
      8,
      8,
      8,
      8,
      8,
      8,
      8,
      8,
      8,
      8,
      8,
      8,
      8,
      8,
      8,
      8,
      8,
      8,
      8,
      8,
      8,
      8,
      8,
      8,
      5,
      5,
      5,
      5,
      5,
      5,
      5,
      5,
      5,
      5,
      5,
      5,
      5,
      5,
      5,
      5,
      5,
      5,
      5,
      5,
      5,
      5,
      5,
      5,
      5,
      5,
      5,
      5,
      5,
      5,
      5,
      5,
      5,
      5,
      5,
      5,
      5,
      5,
      5,
      5,
      5,
      5,
      5,
      5,
      5,
      5,
      5,
      5,
      5,
      5,
      5,
      5,
      5,
      5,
      5,
      5,
      5,
      5,
      5,
      5,
      5,
      5,
      5,
      5,
      5,
      5,
      5,
      5,
      5,
      5,
      5,
      5,
      5,
      5,
      5,
      5,
      5,
      5,
      5,
      5,
      5,
      5,
      5,
      5,
      5,
      5,
      5,
      5,
      5,
      5,
      5,
      5,
      5,
      5,
      5,
      5,
      5,
      5,
      5,
      5,
      5,
      5,
      5,
      5,
      5,
      5,
      5,
      5,
      5,
      5,
      5,
      5,
      5,
      5,
      5,
      5,
      5,
      5,
      5,
      5,
      5,
      5,
      5,
      5,
      5,
      5,
      5,
      5,
      5,
      5,
      5,
      5,
      5,
      5,
      5,
      11,
      11,
      11,
      11,
      11,
      11,
      11,
      11,
      11,
      11,
      11,
      11,
      11,
      11,
      11,
      11,
      11,
      11,
      11,
      11,
      11,
      11,
      11,
      11,
      11,
      11,
      11,
      11,
      11,
      11,
      11,
      11,
      11,
      11,
      11,
      11,
      11,
      11,
      11,
      11,
      11,
      11,
      11,
      11,
      11,
      11,
      11,
      11,
      11,
      11,
      11,
      11,
      11,
      11,
      11,
      11,
      11,
      11,
      11,
      11,
      11,
      11,
      11,
      11,
      11,
      11,
      11,
      11,
      11,
      11,
      11,
      11,
      11,
      11,
      11,
      11,
      11,
      11,
      11,
      11,
      11,
      11,
      11,
      11,
      11,
      11,
      11,
      11,
      11,
      11,
      11,
      11,
      11,
      11,
      11,
      11,
      11,
      11,
      11,
      11,
      11,
      11,
      11,
      11,
      11,
      11,
      11,
      11,
      11,
      11,
      11,
      11,
      11,
      11,
      11,
      11,
      11,
      11,
      11,
      11,
      11,
      11,
      11,
      11,
      11,
      11,
      11,
      11,
      11,
      11,
      11,
      11,
      11,
      11,
      11,
      11,
      0,
      0,
      0,
      0,
      0,
      0,
      0,
      0,
      0,
      0,
      0,
      0,
      0,
      0,
      0,
      0,
      0,
      0,
      0,
      0,
      0,
      0,
      0,
      0,
      0,
      0,
      0,
      0,
      0,
      0,
      0,
      0,
      0,
      0,
      0,
      0,
      0,
      0,
      0,
      0,
      0,
      0,
      0,
      0,
      0,
      0,
      0,
      0,
      0,
      0,
      0,
      0,
      0,
      0,
      0,
      0,
      0,
      0,
      0,
      0,
      0,
      0,
      0,
      0,
      0,
      0,
      0,
      0,
      0,
      0,
      0,
      0,
      0,
      0,
      0,
      0,
      0,
      0,
      0,
      0,
      0,
      0,
      0,
      0,
      0,
      0,
      0,
      0,
      0,
      0,
      0,
      0,
      0,
      0,
      0,
      0,
      0,
      0,
      0,
      0,
      0,
      0,
      0,
      0,
      0,
      0,
      0,
      0,
      0,
      3,
      3,
      3,
      3,
      3,
      3,
      3,
      3,
      3,
      3,
      3,
      3,
      3,
      3,
      3,
      3,
      3,
      3,
      3,
      3,
      3,
      3,
      3,
      3,
      3,
      3,
      3,
      3,
      3,
      3,
      3,
      3,
      3,
      3,
      3,
      3,
      3,
      3,
      3,
      3,
      3,
      3,
      3,
      3,
      3,
      3,
      3,
      3,
      3,
      3,
      3,
      3,
      3,
      3,
      3,
      3,
      3,
      3,
      3,
      3,
      3,
      3,
      3,
      3,
      3,
      3,
      3,
      3,
      3,
      3,
      3,
      3,
      3,
      3,
      3,
      3,
      3,
      3,
      3,
      3,
      3,
      3,
      3,
      3,
      3,
      3,
      3,
      3,
      3,
      3,
      3,
      3,
      3,
      3,
      3,
      3,
      3,
      3,
      3,
      3,
      3,
      3,
      3,
      3,
      3,
      3,
      3,
      3,
      3,
      3,
      3,
      3,
      3,
      3,
      3,
      3,
      3,
      3,
      3,
      3,
      3,
      3,
      3,
      3,
      3,
      3,
      3,
      3,
      3,
      3,
      3,
      3,
      3,
      3,
      12,
      12,
      12,
      12,
      12,
      12,
      12,
      12,
      12,
      12,
      12,
      12,
      12,
      12,
      12,
      12,
      12,
      12,
      12,
      12,
      12,
      12,
      12,
      12,
      12,
      12,
      12,
      12,
      12,
      12,
      12,
      12,
      12,
      12,
      12,
      12,
      12,
      12,
      12,
      12,
      12,
      12,
      12,
      12,
      12,
      12,
      12,
      12,
      12,
      12,
      12,
      12,
      12,
      12,
      12,
      12,
      12,
      12,
      12,
      12,
      12,
      12,
      12,
      12,
      12,
      12,
      12,
      12,
      12,
      12,
      12,
      12,
      12,
      12,
      12,
      12,
      12,
      12,
      12,
      12,
      12,
      12,
      12,
      12,
      12,
      12,
      12,
      12,
      12,
      12,
      12,
      12,
      12,
      12,
      12,
      12,
      12,
      12,
      12,
      12,
      12,
      12,
      12,
      12,
      12,
      12,
      12,
      12,
      12,
      12,
      12,
      12,
      12,
      12,
      12,
      12,
      12,
      12,
      12,
      12,
      12,
      12,
      12,
      12,
      12,
      12,
      12,
      12,
      12,
      12,
      12,
      12,
      12,
      12,
      12,
      4,
      4,
      4,
      4,
      4,
      4,
      4,
      4,
      4,
      4,
      4,
      4,
      4,
      4,
      4,
      4,
      4,
      4,
      4,
      4,
      4,
      4,
      4,
      4,
      4,
      4,
      4,
      4,
      4,
      4,
      4,
      4,
      4,
      4,
      4,
      4,
      4,
      4,
      4,
      4,
      4,
      4,
      4,
      4,
      4,
      4,
      4,
      4,
      4,
      4,
      4,
      4,
      4,
      4,
      4,
      4,
      4,
      4,
      4,
      4,
      4,
      4,
      4,
      4,
      4,
      4,
      4,
      4,
      4,
      4,
      4,
      4,
      4,
      4,
      4,
      4,
      4,
      4,
      4,
      4,
      4,
      4,
      4,
      4,
      4,
      4,
      4,
      4,
      4,
      4,
      4,
      4,
      4,
      4,
      4,
      4,
      4,
      4,
      4,
      4,
      4,
      4,
      4,
      4,
      4,
      4,
      4,
      4,
      4,
      4,
      4,
      4,
      4,
      4,
      4,
      4,
      4,
      4,
      4,
      4,
      4,
      4,
      4,
      4,
      4,
      4,
      4,
      4,
      4,
      4,
      4,
      4,
      10,
      10,
      10,
      10,
      10,
      10,
      10,
      10,
      10,
      10,
      10,
      10,
      10,
      10,
      10,
      10,
      10,
      10,
      10,
      10,
      10,
      10,
      10,
      10,
      10,
      10,
      10,
      10,
      10,
      10,
      10,
      10,
      10,
      10,
      10,
      10,
      10,
      10,
      10,
      10,
      10,
      10,
      10,
      10,
      10,
      10,
      10,
      10,
      10,
      10,
      10,
      10,
      10,
      10,
      10,
      10,
      10,
      10,
      10,
      10,
      10,
      10,
      10,
      10,
      10,
      10,
      10,
      10,
      10,
      10,
      10,
      10,
      10,
      10,
      10,
      10,
      10,
      10,
      10,
      10,
      10,
      10,
      10,
      10,
      10,
      10,
      10,
      10,
      10,
      10,
      10,
      10,
      10,
      10,
      10,
      10,
      10,
      10,
      10,
      10,
      10,
      10,
      10,
      10,
      10,
      10,
      10,
      10,
      10,
      10,
      10,
      10,
      10,
      10,
      10,
      10,
      10,
      10,
      10,
      10,
      10,
      10,
      10,
      10,
      10,
      10,
      10,
      10,
      10,
      10,
      10,
      10,
      10,
      10,
      10,
      10,
      10,
      1,
      1,
      1,
      1,
      1,
      1,
      1,
      1,
      1,
      1,
      1,
      1,
      1,
      1,
      1,
      1,
      1,
      1,
      1,
      1,
      1,
      1,
      1,
      1,
      1,
      1,
      1,
      1,
      1,
      1,
      1,
      1,
      1,
      1,
      1,
      1,
      1,
      1,
      1,
      1,
      1,
      1,
      1,
      1,
      1,
      1,
      1,
      1,
      1,
      1,
      1,
      1,
      1,
      1,
      1,
      1,
      1,
      1,
      1,
      1,
      1,
      1,
      1,
      1,
      1,
      1,
      1,
      1,
      1,
      1,
      1,
      1,
      1,
      1,
      1,
      1,
      1,
      1,
      1,
      1,
      1,
      1,
      1,
      1,
      1,
      1,
      1,
      1,
      1,
      1,
      1,
      1,
      1,
      1,
      1,
      1,
      1,
      1,
      1,
      1,
      1,
      1,
      1,
      1,
      1,
      1,
      1,
      1,
      1,
      1,
      1,
      1,
      1,
      1,
      1,
      1,
      1,
      1,
      1,
      1,
      1,
      1,
      1,
      1,
      1,
      1,
      1,
      1,
      1,
      1,
      1,
      1,
      1,
      14,
      14,
      14,
      14,
      14,
      14,
      14,
      14,
      14,
      14,
      14,
      14,
      14,
      14,
      14,
      14,
      14,
      14,
      14,
      14,
      14,
      14,
      14,
      14,
      14,
      14,
      14,
      14,
      14,
      14,
      14,
      14,
      14,
      14,
      14,
      14,
      14,
      14,
      14,
      14,
      14,
      14,
      14,
      14,
      14,
      14,
      14,
      14,
      14,
      14,
      14,
      14,
      14,
      14,
      14,
      14,
      14,
      14,
      14,
      14,
      14,
      14,
      14,
      14,
      14,
      14,
      14,
      14,
      14,
      14,
      14,
      14,
      14,
      14,
      14,
      14,
      14,
      14,
      14,
      14,
      14,
      14,
      14,
      14,
      14,
      14,
      14,
      14,
      14,
      14,
      14,
      14,
      14,
      14,
      14,
      14,
      14,
      14,
      14,
      14,
      14,
      14,
      14,
      14,
      14,
      14,
      14,
      14,
      14,
      14,
      14,
      14,
      14,
      14,
      14,
      14,
      14,
      14,
      14,
      14,
      14,
      14,
      14,
      14,
      14,
      14,
      14,
      14,
      14,
      14,
      14,
      14,
      14,
      14,
      14
   ],
   "em_f1_micro": [
      0.7293646823411706,
      0.6418209104552276,
      0.08354177088544272,
      0.11855927963981992,
      0.47473736868434224,
      0.1935967983991996,
      0.6323161580790395,
      0.16908454227113556,
      0.39419709854927465,
      0.3231615807903952
   ],
   "em_f1_macro": [
      0.7290573191821413,
      0.6411952252523359,
      0.08357188187812951,
      0.11874022635088391,
      0.4774018298070706,
      0.19368844177917907,
      0.632447171140857,
      0.1691431267558413,
      0.3953617028862482,
      0.32259002159191746
   ],
   "em_f1_weighted": [
      0.7290911764752248,
      0.6417894194281998,
      0.08332458499794929,
      0.11899384766894192,
      0.4773235188343493,
      0.19351525095687422,
      0.6336965497176137,
      0.16816526834416234,
      0.39626188895666004,
      0.32402813927571916
   ]
}